[
  {
    "doc_id": "IRP PowerPoint Presentation-Daidan Lu.pdf",
    "chunk_idx": 0,
    "id": "IRP PowerPoint Presentation-Daidan Lu.pdf:0:3c3daba7"
  },
  {
    "doc_id": "IRP PowerPoint Presentation-Daidan Lu.pdf",
    "chunk_idx": 1,
    "id": "IRP PowerPoint Presentation-Daidan Lu.pdf:1:499447eb"
  },
  {
    "doc_id": "IRP PowerPoint Presentation-Daidan Lu.pdf",
    "chunk_idx": 2,
    "id": "IRP PowerPoint Presentation-Daidan Lu.pdf:2:43743e88"
  },
  {
    "doc_id": "IRP PowerPoint Presentation-Daidan Lu.pdf",
    "chunk_idx": 3,
    "id": "IRP PowerPoint Presentation-Daidan Lu.pdf:3:398d3c99"
  },
  {
    "doc_id": "IRP PowerPoint Presentation-Daidan Lu.pdf",
    "chunk_idx": 4,
    "id": "IRP PowerPoint Presentation-Daidan Lu.pdf:4:9b88a181"
  },
  {
    "doc_id": "IRP PowerPoint Presentation-Daidan Lu.pdf",
    "chunk_idx": 5,
    "id": "IRP PowerPoint Presentation-Daidan Lu.pdf:5:ecae59c6"
  },
  {
    "doc_id": "IRP PowerPoint Presentation-Daidan Lu.pdf",
    "chunk_idx": 6,
    "id": "IRP PowerPoint Presentation-Daidan Lu.pdf:6:469109b8"
  }
]